vastify/__init__.py
vastify/decorator.py
vastify/dep_tracker.py
vastify/inactivity_monitor.py
vastify/instance.py
vastify/instance_state.py
vastify/investigate.py
vastify/keys.py
vastify/main.py
vastify/patched_vastai/__init__.py
vastify/patched_vastai/vast.py
vastify/patched_vastai/vastai_base.py
vastify/patched_vastai/vastai_sdk.py
vastify/persist.py
vastify/requirements.py
vastify/search.py
vastify/test.py
vastify/test_code.py
vastify-0.4.20.dist-info/METADATA
vastify-0.4.20.dist-info/WHEEL
vastify-0.4.20.dist-info/RECORD
