Metadata-Version: 2.3
Name: vastify
Version: 0.4.20
Summary: Vastify automagically runs your function on a vast.ai GPU cloud machine by using a simple decorator.
Author: PitchAI
Author-email: info@pitchai.net
Requires-Python: >=3.9,<4.0
Classifier: Programming Language :: Python :: 3
Classifier: Programming Language :: Python :: 3.9
Classifier: Programming Language :: Python :: 3.10
Classifier: Programming Language :: Python :: 3.11
Classifier: Programming Language :: Python :: 3.12
Classifier: Programming Language :: Python :: 3.13
Requires-Dist: numpy (>=1.22.4,<2.0.0)
Requires-Dist: paramiko (>=3.5.0,<4.0.0)
Requires-Dist: pydantic (>=2.10.6,<3.0.0)
Requires-Dist: requests (>=2.32.3,<3.0.0)
Requires-Dist: tqdm (>=4.67.1,<5.0.0)
